vuer_cli/__init__.py
vuer_cli/add.py
vuer_cli/envs_publish.py
vuer_cli/envs_pull.py
vuer_cli/main.py
vuer_cli/remove.py
vuer_cli/sync.py
vuer_cli/upgrade.py
vuer_cli/utils.py
vuer_cli-0.0.3.dist-info/METADATA
vuer_cli-0.0.3.dist-info/WHEEL
vuer_cli-0.0.3.dist-info/entry_points.txt
vuer_cli-0.0.3.dist-info/licenses/LICENSE
vuer_cli-0.0.3.dist-info/RECORD
