Metadata-Version: 2.4
Name: vuer-cli
Version: 0.0.3
Summary: A Python CLI for Vuer, a real-time 3D visualization library
Project-URL: Homepage, https://github.com/vuer-ai/vuer-cli
Project-URL: Repository, https://github.com/vuer-ai/vuer-cli
Project-URL: Issues, https://github.com/vuer-ai/vuer-cli/issues
Author-email: Ge Yang <ge.ike.yang@gmail.com>
License: MIT
License-File: LICENSE
Classifier: Development Status :: 3 - Alpha
Classifier: License :: OSI Approved :: MIT License
Classifier: Operating System :: OS Independent
Classifier: Programming Language :: Python
Classifier: Programming Language :: Python :: 3.8
Classifier: Programming Language :: Python :: 3.9
Classifier: Programming Language :: Python :: 3.10
Classifier: Programming Language :: Python :: 3.11
Classifier: Programming Language :: Python :: 3.12
Requires-Python: >=3.8
Requires-Dist: params-proto>=3.0.0rc9
Requires-Dist: requests>=2.31.0
Requires-Dist: tqdm>=4.66.0
Provides-Extra: all
Provides-Extra: docs
Requires-Dist: furo; extra == 'docs'
Requires-Dist: myst-parser; extra == 'docs'
Requires-Dist: sphinx-autobuild; extra == 'docs'
Requires-Dist: sphinx-copybutton; extra == 'docs'
Requires-Dist: sphinx>=4.0; extra == 'docs'
Requires-Dist: tomli>=1.1.0; (python_version < '3.11') and extra == 'docs'
Provides-Extra: example
